pymetrick/__init__.py
pymetrick/autosetup.py
pymetrick/bad_passwords.py
pymetrick/blockchain.py
pymetrick/bucket.py
pymetrick/checkversion.py
pymetrick/common.py
pymetrick/db_sqlite.py
pymetrick/device.py
pymetrick/esc_pos_costants.py
pymetrick/exchequer.py
pymetrick/firestore.py
pymetrick/fiscal.py
pymetrick/fonts.py
pymetrick/fpdf.py
pymetrick/geoippy.py
pymetrick/helpers.py
pymetrick/image.py
pymetrick/ipaddress.py
pymetrick/issue.py
pymetrick/mail.py
pymetrick/php.py
pymetrick/py3k.py
pymetrick/queue.py
pymetrick/reindent.py
pymetrick/routing.py
pymetrick/rst.py
pymetrick/session.py
pymetrick/setup.py
pymetrick/setup_instalacion.py
pymetrick/sitemap.py
pymetrick/speech.py
pymetrick/sqldb.py
pymetrick/translator.py
pymetrick/ttfonts.py
pymetrick/version.py
pymetrick-0.80.10.dist-info/licenses/LICENSE
pymetrick-0.80.10.dist-info/METADATA
pymetrick-0.80.10.dist-info/WHEEL
pymetrick-0.80.10.dist-info/top_level.txt
pymetrick-0.80.10.dist-info/RECORD
