Metadata-Version: 2.4
Name: pymetrick
Version: 0.80.10
Summary: Lightweight web framework
Home-page: https://pythonhosted.org/pymetrick/
Author: Fco. Javier Tamarit V
Author-email: javtamvi@gmail.com
Maintainer: Fco. Javier Tamarit V
Maintainer-email: pymetrick@pymetrick.org
License: GNU/GPLv3
Classifier: Development Status :: 5 - Production/Stable
Classifier: License :: OSI Approved :: GNU Lesser General Public License v3 or later (LGPLv3+)
Classifier: Programming Language :: Python :: 3.11
Classifier: Environment :: Web Environment
Classifier: Topic :: Internet :: WWW/HTTP :: WSGI
License-File: LICENSE
Requires-Dist: numpy
Requires-Dist: openpyxl>=3.1.0
Requires-Dist: Pillow
Requires-Dist: pillow-avif-plugin
Requires-Dist: mysql-connector-python
Requires-Dist: qrcode
Requires-Dist: pyaes
Requires-Dist: six>=1.15.0
Requires-Dist: boto3==1.35.72
Requires-Dist: botocore
Requires-Dist: zeep
Dynamic: author
Dynamic: author-email
Dynamic: classifier
Dynamic: description
Dynamic: description-content-type
Dynamic: home-page
Dynamic: license
Dynamic: license-file
Dynamic: maintainer
Dynamic: maintainer-email
Dynamic: requires-dist
Dynamic: summary
